[
	{
		"__TYPE__": "SharedSliceContent",
		"variation": "default",
		"primary": {
			"heading": {
				"__TYPE__": "StructuredTextContent",
				"value": [
					{
						"type": "heading2",
						"content": {
							"text": "Spoken"
						}
					}
				]
			},
			"description": {
				"__TYPE__": "StructuredTextContent",
				"value": [
					{
						"type": "paragraph",
						"content": {
							"text": "Cillum anim ipsum qui. Lorem eu incididunt et sit anim sunt pariatur eu."
						}
					}
				]
			},
			"map_link": {
				"__TYPE__": "LinkContent",
				"value": {
					"__TYPE__": "ExternalLink",
					"url": "http://twitter.com"
				}
			},
			"sub_heading": {
				"__TYPE__": "StructuredTextContent",
				"value": [
					{
						"type": "paragraph",
						"content": {
							"text": "Qui do Lorem occaecat qui aliquip excepteur ea aliqua."
						}
					}
				]
			}
		},
		"items": [
			{
				"__TYPE__": "GroupItemContent",
				"value": [
					[
						"icon",
						{
							"origin": {
								"id": "main",
								"url": "https://images.unsplash.com/photo-1515378791036-0648a3ef77b2",
								"width": 5616,
								"height": 3744
							},
							"url": "https://images.unsplash.com/photo-1515378791036-0648a3ef77b2",
							"width": 5616,
							"height": 3744,
							"edit": {
								"zoom": 1,
								"crop": {
									"x": 0,
									"y": 0
								},
								"background": "transparent"
							},
							"credits": null,
							"alt": null,
							"__TYPE__": "ImageContent",
							"thumbnails": {}
						}
					],
					[
						"title",
						{
							"__TYPE__": "StructuredTextContent",
							"value": [
								{
									"type": "paragraph",
									"content": {
										"text": "Aliqua ea elit culpa qui labore nostrud esse commodo incididunt proident. Dolore tempor ex ipsum nostrud ullamco veniam voluptate nisi Lorem. Consectetur amet id esse aliquip."
									}
								}
							]
						}
					],
					[
						"details",
						{
							"__TYPE__": "StructuredTextContent",
							"value": [
								{
									"type": "paragraph",
									"content": {
										"text": "Ad ad qui officia aute ex incididunt in sunt et. Id veniam ad nostrud ipsum cillum laboris cillum reprehenderit velit nulla ut excepteur. Ea officia fugiat voluptate et consectetur."
									}
								}
							]
						}
					]
				]
			}
		]
	}
]